FacebookWebBot.py
FacebookWebBot-1.1.0.dist-info/DESCRIPTION.rst
FacebookWebBot-1.1.0.dist-info/METADATA
FacebookWebBot-1.1.0.dist-info/RECORD
FacebookWebBot-1.1.0.dist-info/WHEEL
FacebookWebBot-1.1.0.dist-info/metadata.json
FacebookWebBot-1.1.0.dist-info/top_level.txt
