Metadata-Version: 2.0
Name: FacebookWebBot
Version: 1.1.0
Summary: A python library to automatize facebook without the official API
Home-page: https://github.com/hikaruAi/FacebookBot
Author: Juan José Mendoza
Author-email: contacto.juanmendoza@gmail.com
License: Apache License 2.0
Keywords: Automation,web,social network
Platform: UNKNOWN
Classifier: Development Status :: 4 - Beta
Classifier: Intended Audience :: Developers
Classifier: Topic :: Home Automation
Classifier: License :: OSI Approved :: Apache Software License
Classifier: Programming Language :: Python :: 3
Classifier: Programming Language :: Python :: 3.3
Classifier: Programming Language :: Python :: 3.4
Requires-Dist: selenium
